spaxiom/.DS_Store
spaxiom/__init__.py
spaxiom/actuators/__init__.py
spaxiom/actuators/gpio_output.py
spaxiom/adaptors/__init__.py
spaxiom/adaptors/file_sensor.py
spaxiom/adaptors/gpio_sensor.py
spaxiom/adaptors/mqtt_sensor.py
spaxiom/cli.py
spaxiom/condition.py
spaxiom/config.py
spaxiom/core.py
spaxiom/entities.py
spaxiom/events.py
spaxiom/fusion.py
spaxiom/geo.py
spaxiom/governance/__init__.py
spaxiom/governance/audit.py
spaxiom/governance/authz.py
spaxiom/governance/consent.py
spaxiom/governance/retention.py
spaxiom/intent/__init__.py
spaxiom/intent/adl_tracker.py
spaxiom/intent/fm_steward.py
spaxiom/intent/occupancy_field.py
spaxiom/intent/pattern.py
spaxiom/intent/queue_flow.py
spaxiom/logic.py
spaxiom/model.py
spaxiom/plugins.py
spaxiom/registry.py
spaxiom/runtime.py
spaxiom/safety/__init__.py
spaxiom/safety/ir.py
spaxiom/safety/monitor.py
spaxiom/safety/verify.py
spaxiom/sensor.py
spaxiom/sim/__init__.py
spaxiom/sim/vec_sim.py
spaxiom/summarize.py
spaxiom/temporal.py
spaxiom/tick.py
spaxiom/units.py
spaxiom/zone.py
spaxiom-0.1.0.dist-info/METADATA
spaxiom-0.1.0.dist-info/WHEEL
spaxiom-0.1.0.dist-info/entry_points.txt
spaxiom-0.1.0.dist-info/licenses/LICENSE
spaxiom-0.1.0.dist-info/RECORD
