Metadata-Version: 2.4
Name: spaxiom
Version: 0.1.0
Summary: An embedded domain-specific language for spatial sensor fusion and AI
License: MIT
License-File: LICENSE
Author: Joe Scanlin
Requires-Python: >=3.8,<4.0
Classifier: License :: OSI Approved :: MIT License
Classifier: Programming Language :: Python :: 3
Classifier: Programming Language :: Python :: 3.8
Classifier: Programming Language :: Python :: 3.9
Classifier: Programming Language :: Python :: 3.10
Classifier: Programming Language :: Python :: 3.11
Classifier: Programming Language :: Python :: 3.12
Classifier: Programming Language :: Python :: 3.13
Classifier: Programming Language :: Python :: 3.14
Provides-Extra: gpio
Provides-Extra: mqtt
Requires-Dist: click (>=8.0)
Requires-Dist: gpiozero (>=2.0) ; extra == "gpio"
Requires-Dist: numpy (>=1.23)
Requires-Dist: onnxruntime (>=1.18)
Requires-Dist: paho-mqtt (>=2.0) ; extra == "mqtt"
Requires-Dist: pint (>=0.23)
Requires-Dist: pyyaml (>=6.0)
Requires-Dist: shapely (>=2.0)
